airtouch5py/airtouch5_client.py
airtouch5py/airtouch5_simple_client.py
airtouch5py/data_packet_factory.py
airtouch5py/packet_decoder.py
airtouch5py/packet_encoder.py
airtouch5py/packet_fields.py
airtouch5py/packet_reader.py
airtouch5py/packets/ac_ability.py
airtouch5py/packets/ac_control.py
airtouch5py/packets/ac_error_information.py
airtouch5py/packets/ac_status.py
airtouch5py/packets/console_version.py
airtouch5py/packets/datapacket.py
airtouch5py/packets/zone_control.py
airtouch5py/packets/zone_name.py
airtouch5py/packets/zone_status.py
airtouch5py-0.3.0.dist-info/LICENSE
airtouch5py-0.3.0.dist-info/METADATA
airtouch5py-0.3.0.dist-info/WHEEL
airtouch5py-0.3.0.dist-info/RECORD
